venubasicmath/__init__.py
venubasicmath/addition.py
venubasicmath/mult.py
venubasicmath/sub.py
venubasicmath-0.0.1.dist-info/METADATA
venubasicmath-0.0.1.dist-info/WHEEL
venubasicmath-0.0.1.dist-info/top_level.txt
venubasicmath-0.0.1.dist-info/RECORD
